CHANGELOG.txt
LICENSE.txt
MANIFEST.in
README.txt
setup.py
test.py
clinton_pyt_images_trainer/__init__.py
clinton_pyt_images_trainer.egg-info/PKG-INFO
clinton_pyt_images_trainer.egg-info/SOURCES.txt
clinton_pyt_images_trainer.egg-info/dependency_links.txt
clinton_pyt_images_trainer.egg-info/top_level.txt