Metadata-Version: 2.1
Name: clinton-pyt-images-trainer
Version: 0.0.2
Summary: PyTorch Images Trainer Function
Home-page: 
Author: Clinton Nyaore
Author-email: cnyaore@gmail.com
License: MIT
Keywords: pytorch
Platform: UNKNOWN
Classifier: Development Status :: 5 - Production/Stable
Classifier: Intended Audience :: Education
Classifier: Operating System :: Microsoft :: Windows :: Windows 10
Classifier: License :: OSI Approved :: MIT License
Classifier: Programming Language :: Python :: 3
License-File: LICENSE.txt
